ward/__init__.py
ward/__main__.py
ward/_collect.py
ward/_config.py
ward/_debug.py
ward/_diff.py
ward/_errors.py
ward/_fixtures.py
ward/_rewrite.py
ward/_run.py
ward/_suite.py
ward/_terminal.py
ward/_testing.py
ward/_utilities.py
ward/_ward_version.py
ward/config.py
ward/expect.py
ward/fixtures.py
ward/hooks.py
ward/models.py
ward/py.typed
ward/testing.py
ward-0.68.0b0.dist-info/LICENSE
ward-0.68.0b0.dist-info/METADATA
ward-0.68.0b0.dist-info/WHEEL
ward-0.68.0b0.dist-info/entry_points.txt
ward-0.68.0b0.dist-info/RECORD
