Metadata-Version: 2.1
Name: ward
Version: 0.68.0b0
Summary: A modern Python testing framework
Home-page: https://ward.readthedocs.io
License: MIT
Keywords: test,testing,quality-assurance,cli,python3
Author: Darren Burns
Author-email: darrenb900@gmail.com
Maintainer: Darren Burns
Maintainer-email: darrenb900@gmail.com
Requires-Python: >=3.7.8,<4.0.0
Classifier: Development Status :: 4 - Beta
Classifier: Environment :: Console
Classifier: Intended Audience :: Developers
Classifier: License :: OSI Approved :: MIT License
Classifier: Operating System :: OS Independent
Classifier: Programming Language :: Python :: 3
Classifier: Programming Language :: Python :: 3.8
Classifier: Programming Language :: Python :: 3.9
Classifier: Programming Language :: Python :: 3.10
Classifier: Programming Language :: Python :: 3.11
Classifier: Programming Language :: Python :: 3.12
Classifier: Topic :: Software Development :: Libraries :: Python Modules
Classifier: Topic :: Software Development :: Quality Assurance
Classifier: Topic :: Software Development :: Testing
Requires-Dist: click (>=7,<9)
Requires-Dist: click-completion (>=0.5.2,<0.6.0)
Requires-Dist: click-default-group (>=1.2.2,<2.0.0)
Requires-Dist: cucumber-tag-expressions (>=2.0.0,<5.0.0)
Requires-Dist: pluggy (>=0.13.1,<2.0.0)
Requires-Dist: pprintpp (>=0.4.0,<0.5.0)
Requires-Dist: rich (>=12.2.0)
Requires-Dist: tomli (>=1.0.0,<3.0.0)
Project-URL: Documentation, https://ward.readthedocs.io
Project-URL: Repository, https://github.com/darrenburns/ward
